open_telemetry_kit/__init__.py
open_telemetry_kit/assparser.py
open_telemetry_kit/blackvueparser.py
open_telemetry_kit/csvparser.py
open_telemetry_kit/detector.py
open_telemetry_kit/element.py
open_telemetry_kit/elements.py
open_telemetry_kit/gpxparser.py
open_telemetry_kit/klv_common.py
open_telemetry_kit/klvparser.py
open_telemetry_kit/kmlparser.py
open_telemetry_kit/misb_0601.py
open_telemetry_kit/packet.py
open_telemetry_kit/parser.py
open_telemetry_kit/srtparser.py
open_telemetry_kit/telemetry.py
open_telemetry_kit/writers.py
open_telemetry_kit-0.2.6.4.dist-info/LICENSE
open_telemetry_kit-0.2.6.4.dist-info/METADATA
open_telemetry_kit-0.2.6.4.dist-info/WHEEL
open_telemetry_kit-0.2.6.4.dist-info/top_level.txt
open_telemetry_kit-0.2.6.4.dist-info/RECORD
