Metadata-Version: 2.1
Name: open-telemetry-kit
Version: 0.2.6.4
Summary: Open source package for extracting and parsing telemetry associated with video streams and converting to common formats.
Home-page: https://github.com/Hivemapper/open-telemetry-kit
Author: Hivemapper
Author-email: adam@hivemapper.com
License: UNKNOWN
Platform: UNKNOWN
Classifier: Development Status :: 3 - Alpha
Classifier: Programming Language :: Python :: 3
Classifier: Intended Audience :: Developers
Classifier: Operating System :: POSIX :: Linux
Classifier: Topic :: Multimedia :: Video
Classifier: Topic :: Scientific/Engineering :: GIS
Classifier: Topic :: Scientific/Engineering :: Information Analysis
Classifier: Topic :: Software Development :: Libraries
Classifier: Topic :: Text Processing
Requires-Python: >=3.6
